LICENSE
MANIFEST.in
README.md
setup.py
simulate.py
scripts/tarsnapper
tarsnapper/__init__.py
tarsnapper/config.py
tarsnapper/expire.py
tarsnapper/script.py
tarsnapper/test.py
tarsnapper.egg-info/PKG-INFO
tarsnapper.egg-info/SOURCES.txt
tarsnapper.egg-info/dependency_links.txt
tarsnapper.egg-info/entry_points.txt
tarsnapper.egg-info/not-zip-safe
tarsnapper.egg-info/requires.txt
tarsnapper.egg-info/top_level.txt
tests/__init__.py
tests/test_config.py
tests/test_expire.py
tests/test_script.py