Metadata-Version: 1.1
Name: tarsnapper
Version: 0.5.0
Summary: Manages tarsnap backups
Home-page: http://github.com/miracle2k/tarsnapper
Author: Michael Elsdoerfer
Author-email: michael@elsdoerfer.com
License: BSD
Platform: UNKNOWN
Classifier: License :: OSI Approved :: BSD License
Classifier: Programming Language :: Python :: 2
Classifier: Programming Language :: Python :: 3
